tchotcho/__init__.py
tchotcho/__main__.py
tchotcho/config.py
tchotcho/log.py
tchotcho/rsa.py
tchotcho/tropo.py
tchotcho/util.py
tchotcho/action/__init__.py
tchotcho/action/info.py
tchotcho/action/key.py
tchotcho/action/shell.py
tchotcho/action/spot.py
tchotcho/action/stack.py
tchotcho-0.7.0.dist-info/METADATA
tchotcho-0.7.0.dist-info/WHEEL
tchotcho-0.7.0.dist-info/entry_points.txt
tchotcho-0.7.0.dist-info/top_level.txt
tchotcho-0.7.0.dist-info/RECORD
