Metadata-Version: 2.1
Name: tchotcho
Version: 0.7.0
Summary: tchotcho
Home-page: https://gitlab.com/delijati/tchotcho
Author: Josip Delic
License: UNKNOWN
Platform: UNKNOWN
Classifier: Programming Language :: Python :: 3.6
Classifier: Programming Language :: Python :: 3.7
Classifier: Operating System :: OS Independent
Requires-Dist: boto3
Requires-Dist: troposphere
Requires-Dist: awacs
Requires-Dist: click
Requires-Dist: requests
Requires-Dist: colorlog
Requires-Dist: colorama
Requires-Dist: tabulate
Requires-Dist: pydantic
Requires-Dist: pandas
Requires-Dist: pycryptodome
Requires-Dist: attrs
Provides-Extra: tests
Requires-Dist: pytest ; extra == 'tests'
Requires-Dist: pytest-cov ; extra == 'tests'
Requires-Dist: pytest-env ; extra == 'tests'
Requires-Dist: moto ; extra == 'tests'
